lib/__init__.py
lib/host.py
lib/ixia.py
lib/session.py
lib/mdc/__init__.py
guerrillaDemo-0.1.0.dist-info/METADATA
guerrillaDemo-0.1.0.dist-info/WHEEL
guerrillaDemo-0.1.0.dist-info/top_level.txt
guerrillaDemo-0.1.0.dist-info/RECORD
